Metadata-Version: 2.1
Name: llm-embed-onnx
Version: 0.1
Summary: Run embedding models using ONNX
Author: Simon Willison
License: Apache-2.0
Project-URL: Homepage, https://github.com/simonw/llm-embed-onnx
Project-URL: Changelog, https://github.com/simonw/llm-embed-onnx/releases
Project-URL: Issues, https://github.com/simonw/llm-embed-onnx/issues
Project-URL: CI, https://github.com/simonw/llm-embed-onnx/actions
Classifier: License :: OSI Approved :: Apache Software License
Requires-Python: >=3.9
License-File: LICENSE
Requires-Dist: llm
Requires-Dist: onnx-embedding-models ==0.0.5
Provides-Extra: test
Requires-Dist: pytest ; extra == 'test'
